rsi_scraper/__init__.py
rsi_scraper/connector.py
rsi_scraper/interface.py
rsi_scraper/organization.py
rsi_scraper/progress_tracker.py
rsi_scraper/roadmap.py
rsi_scraper/ship.py
rsi_scraper/starmap.py
rsi_scraper/stats.py
rsi_scraper/telemetry.py
rsi_scraper/user.py
rsi_scraper/version.py
tests/__init__.py
tests/test_connector.py
tests/test_organization.py
tests/test_organization_members.py
tests/test_progress_tracker.py
tests/test_roadmap.py
tests/test_ship.py
tests/test_starmap.py
tests/test_stats.py
tests/test_telemetry.py
tests/test_user.py
tests/test_version.py
tests/validator.py
rsi_scraper-0.6.8.dist-info/LICENSE
rsi_scraper-0.6.8.dist-info/METADATA
rsi_scraper-0.6.8.dist-info/WHEEL
rsi_scraper-0.6.8.dist-info/top_level.txt
rsi_scraper-0.6.8.dist-info/RECORD
