Metadata-Version: 2.1
Name: rsi-scraper
Version: 0.6.8
Summary: Web scaper for RSI
Home-page: https://github.com/Dymerz/RSI-Scraper
Author: Urbain Corentin
Project-URL: Bug Tracker, https://github.com/Dymerz/RSI-Scraper/issues
Project-URL: Chat, https://github.com/Dymerz/RSI-Scraper/discussions
Keywords: starcitizen robertsspaceindustries rsi scraper scraping
Classifier: Topic :: Software Development :: Libraries :: Python Modules
Classifier: License :: OSI Approved :: GNU General Public License v3 (GPLv3)
Classifier: Operating System :: OS Independent
Classifier: Programming Language :: Python :: 3.7
Classifier: Programming Language :: Python :: 3.8
Classifier: Programming Language :: Python :: 3.9
Requires-Python: >=3.7
License-File: LICENSE
Requires-Dist: requests (>=2.25.1)
Requires-Dist: lxml (>=4.6.3)
